msrks_hello/__init__.py
msrks_hello/main.py
pypi_hello/__init__.py
pypi_hello/main.py
msrks_hello-0.0.3.dist-info/METADATA
msrks_hello-0.0.3.dist-info/WHEEL
msrks_hello-0.0.3.dist-info/entry_points.txt
msrks_hello-0.0.3.dist-info/top_level.txt
msrks_hello-0.0.3.dist-info/RECORD
