Metadata-Version: 2.1
Name: msrks-hello
Version: 0.0.3
Requires-Dist: requests
